blink/__init__.py
blink/blink.py
blink/script.py
tests/__init__.py
tests/test_all.py
blink_cameras-0.3.13.dist-info/LICENSE
blink_cameras-0.3.13.dist-info/METADATA
blink_cameras-0.3.13.dist-info/WHEEL
blink_cameras-0.3.13.dist-info/top_level.txt
blink_cameras-0.3.13.dist-info/RECORD
