Metadata-Version: 2.1
Name: blink-cameras
Version: 0.3.13
Summary: Python API for the Blink Home Security Camera System
Home-page: UNKNOWN
Author: Derek Anderson
Author-email: public@kered.org
License: UNKNOWN
Platform: UNKNOWN
Classifier: Programming Language :: Python :: 3
Classifier: License :: OSI Approved :: GNU Lesser General Public License v2 or later (LGPLv2+)
Classifier: Operating System :: OS Independent
Requires-Dist: python-dateutil
Requires-Dist: pyyaml
Requires-Dist: requests
